Metadata-Version: 2.1
Name: pandoc-attrs
Version: 0.1.7
Summary: An Attribute class to be used with pandocfilters
Home-page: http://github.com/kiwi0fruit/pandoc-attrs
Author: Aaron O'Leary
Author-email: dev@aaren.me
License: BSD 2-Clause
Platform: UNKNOWN
